{"URL":"http://bbs.csdn.net/topics/391932935","author":"","encoding":"utf-8","label":"[\"颜色识别\",\"机器视觉\",\"opencv\"]","pageWeigh":"1","parentPageCount":"0","text":" 取消关注 关注 qq 21741729 qq 21741729 本版等级 本版专家分 0 结帖率 0 楼主 发表于 2016 04 12 09 40 58 颜色识别 机器视觉 opencv 求采样程序及识别程序 这个问题好像很难 不知道有没有高手会的 多谢啦 更多 分享到 对我有用 0 丢个板砖 0 引用 举报 编辑 删除 管理 回复次数 4 相关知识库 操作系统 Redis 嵌入式开发 Cocos引擎 取消关注 关注 sunny7862632 sunny7862632 本版等级 本版专家分 238 结帖率 0 1 得分 0 回复于 2016 04 12 16 41 24 不难 但是免费的就难了 对我有用 0 丢个板砖 0 引用 举报 编辑 删除 管理 取消关注 关注 linjimu linjimu 本版等级 本版专家分 0 结帖率 98 98 2 得分 0 回复于 2016 04 26 19 28 42 钱的种类不多 找出所有种类的共同特征 比如尺寸比例 颜色等 二值化 阀值 差值 或者直方图的应用 各种边缘检测 傅里叶描述子等的应用 检测出所在位置 再精准识别 判断是那种钱币 只会思路 共同学习 对我有用 0 丢个板砖 0 引用 举报 编辑 删除 管理 取消关注 关注 waynewuhao waynewuhao 本版等级 本版专家分 0 结帖率 0 3 得分 0 回复于 2016 05 05 16 42 49 很容易 但是免费的就难了 对我有用 0 丢个板砖 0 引用 举报 编辑 删除 管理 取消关注 关注 heroinsky heroinsky 本版等级 本版专家分 0 结帖率 0 4 得分 0 回复于 2016 06 10 21 12 40 我们有现成纸币识别方案 需要联系QQ460222731 对我有用 0 丢个板砖 0 引用 举报 编辑 删除 管理","timestamp":"201606122201","title":" 求如何识别1元10元5元50元100元的程序 Java或c 多谢啦"}